pymc_marketing/__init__.py
pymc_marketing/causal_utils.py
pymc_marketing/constants.py
pymc_marketing/decorators.py
pymc_marketing/deserialize.py
pymc_marketing/hsgp_kwargs.py
pymc_marketing/metrics.py
pymc_marketing/mlflow.py
pymc_marketing/model_builder.py
pymc_marketing/model_config.py
pymc_marketing/model_graph.py
pymc_marketing/paths.py
pymc_marketing/plot.py
pymc_marketing/prior.py
pymc_marketing/py.typed
pymc_marketing/pytensor_utils.py
pymc_marketing/special_priors.py
pymc_marketing/utils.py
pymc_marketing/version.py
pymc_marketing/bass/__init__.py
pymc_marketing/bass/model.py
pymc_marketing/clv/__init__.py
pymc_marketing/clv/distributions.py
pymc_marketing/clv/plotting.py
pymc_marketing/clv/utils.py
pymc_marketing/clv/models/__init__.py
pymc_marketing/clv/models/basic.py
pymc_marketing/clv/models/beta_geo.py
pymc_marketing/clv/models/beta_geo_beta_binom.py
pymc_marketing/clv/models/gamma_gamma.py
pymc_marketing/clv/models/modified_beta_geo.py
pymc_marketing/clv/models/pareto_nbd.py
pymc_marketing/clv/models/shifted_beta_geo.py
pymc_marketing/customer_choice/__init__.py
pymc_marketing/customer_choice/mnl_logit.py
pymc_marketing/customer_choice/mv_its.py
pymc_marketing/customer_choice/nested_logit.py
pymc_marketing/customer_choice/synthetic_data.py
pymc_marketing/data/__init__.py
pymc_marketing/data/fivetran.py
pymc_marketing/mmm/__init__.py
pymc_marketing/mmm/additive_effect.py
pymc_marketing/mmm/base.py
pymc_marketing/mmm/budget_optimizer.py
pymc_marketing/mmm/causal.py
pymc_marketing/mmm/constraints.py
pymc_marketing/mmm/evaluation.py
pymc_marketing/mmm/events.py
pymc_marketing/mmm/fourier.py
pymc_marketing/mmm/hsgp.py
pymc_marketing/mmm/lift_test.py
pymc_marketing/mmm/linear_regression.py
pymc_marketing/mmm/linear_trend.py
pymc_marketing/mmm/media_transformation.py
pymc_marketing/mmm/mmm.py
pymc_marketing/mmm/multidimensional.py
pymc_marketing/mmm/plot.py
pymc_marketing/mmm/preprocessing.py
pymc_marketing/mmm/scaling.py
pymc_marketing-0.17.1.dist-info/METADATA
pymc_marketing-0.17.1.dist-info/WHEEL
pymc_marketing-0.17.1.dist-info/licenses/LICENSE
pymc_marketing-0.17.1.dist-info/RECORD
