Metadata-Version: 2.4
Name: pymc-marketing
Version: 0.17.1
Summary: Marketing Statistical Models in PyMC
Project-URL: repository, https://github.com/pymc-labs/pymc-marketing
Project-URL: homepage, https://www.pymc-marketing.io
Maintainer-email: PyMC Labs <info@pymc-labs.com>
License:                                  Apache License
License-File: LICENSE
Classifier: Development Status :: 5 - Production/Stable
Classifier: Intended Audience :: Science/Research
Classifier: License :: OSI Approved :: Apache Software License
Classifier: Operating System :: OS Independent
Classifier: Programming Language :: Python
Classifier: Programming Language :: Python :: 3
Classifier: Programming Language :: Python :: 3.11
Classifier: Programming Language :: Python :: 3.12
Classifier: Programming Language :: Python :: 3.13
Classifier: Topic :: Scientific/Engineering
Classifier: Topic :: Scientific/Engineering :: Mathematics
Classifier: Typing :: Typed
Requires-Python: >=3.11
Requires-Dist: arviz>=0.13.0
Requires-Dist: matplotlib>=3.5.1
Requires-Dist: numpy>=1.17
Requires-Dist: pandas
Requires-Dist: preliz>=0.20.0
Requires-Dist: pydantic>=2.1.0
Requires-Dist: pymc-extras>=0.4.0
Requires-Dist: pymc>=5.24.1
Requires-Dist: pyprojroot
Requires-Dist: pytensor>=2.31.3
Requires-Dist: scikit-learn>=1.1.1
Requires-Dist: seaborn>=0.12.2
Requires-Dist: xarray-einstats>=0.5.1
Requires-Dist: xarray>=2024.1.0
Provides-Extra: dag
Requires-Dist: dowhy; extra == 'dag'
Requires-Dist: networkx; extra == 'dag'
Requires-Dist: osqp<1.0.0,>=0.6.2; extra == 'dag'
Requires-Dist: pygraphviz; extra == 'dag'
Provides-Extra: docs
Requires-Dist: blackjax; extra == 'docs'
Requires-Dist: dowhy; extra == 'docs'
Requires-Dist: fastprogress; extra == 'docs'
Requires-Dist: graphviz; extra == 'docs'
Requires-Dist: ipython!=8.7.0; extra == 'docs'
Requires-Dist: ipywidgets; extra == 'docs'
Requires-Dist: labs-sphinx-theme; extra == 'docs'
Requires-Dist: lifetimes; extra == 'docs'
Requires-Dist: mlflow>=2.0.0; extra == 'docs'
Requires-Dist: myst-nb>=1.1.2; extra == 'docs'
Requires-Dist: myst-parser; extra == 'docs'
Requires-Dist: networkx; extra == 'docs'
Requires-Dist: numba; extra == 'docs'
Requires-Dist: numpydoc; extra == 'docs'
Requires-Dist: numpyro; extra == 'docs'
Requires-Dist: nutpie; extra == 'docs'
Requires-Dist: osqp<1.0.0,>=0.6.2; extra == 'docs'
Requires-Dist: preliz>=0.20.0; extra == 'docs'
Requires-Dist: pylint; extra == 'docs'
Requires-Dist: sphinx; extra == 'docs'
Requires-Dist: sphinx-autodoc-typehints; extra == 'docs'
Requires-Dist: sphinx-copybutton; extra == 'docs'
Requires-Dist: sphinx-design; extra == 'docs'
Requires-Dist: sphinx-notfound-page; extra == 'docs'
Requires-Dist: sphinx-remove-toctrees; extra == 'docs'
Requires-Dist: sphinxext-opengraph; extra == 'docs'
Requires-Dist: watermark; extra == 'docs'
Provides-Extra: lint
Requires-Dist: mypy; extra == 'lint'
Requires-Dist: pandas-stubs; extra == 'lint'
Requires-Dist: pre-commit>=2.19.0; extra == 'lint'
Requires-Dist: ruff>=0.1.4; extra == 'lint'
Provides-Extra: test
Requires-Dist: blackjax; extra == 'test'
Requires-Dist: dowhy; extra == 'test'
Requires-Dist: graphviz>=0.20.1; extra == 'test'
Requires-Dist: jax<0.7.0; extra == 'test'
Requires-Dist: lifetimes==0.11.3; extra == 'test'
Requires-Dist: mlflow>=2.0.0; extra == 'test'
Requires-Dist: networkx; extra == 'test'
Requires-Dist: numpyro; extra == 'test'
Requires-Dist: nutpie; extra == 'test'
Requires-Dist: osqp<1.0.0,>=0.6.2; extra == 'test'
Requires-Dist: papermill; extra == 'test'
Requires-Dist: preliz>=0.20.0; extra == 'test'
Requires-Dist: pygraphviz; extra == 'test'
Requires-Dist: pyprojroot; extra == 'test'
Requires-Dist: pytest-cov>=3.0.0; extra == 'test'
Requires-Dist: pytest-mock>=3.14.0; extra == 'test'
Requires-Dist: pytest>=7.0.1; extra == 'test'
